{
  "kind": "collectionType",
  "collectionName": "companies",
  "info": {
    "singularName": "company",
    "pluralName": "companies",
    "displayName": "Companies",
    "description": ""
  },
  "options": {
    "draftAndPublish": false,
    "privateAttributes": [
      "publishedAt",
      "createdAt",
      "updatedAt",
      "locale",
      "localizations"
    ]
  },
  "pluginOptions": {},
  "attributes": {
    "name": {
      "type": "string"
    },
    "logo": {
      "type": "media",
      "multiple": true,
      "required": false,
      "allowedTypes": [
        "images"
      ]
    },
    "overview": {
      "type": "text"
    },
    "contactHR": {
      "type": "email"
    },
    "valuePropositiion": {
      "type": "text"
    },
    "website": {
      "type": "string"
    },
    "active": {
      "type": "boolean",
      "default": true
    },
    "industry": {
      "type": "relation",
      "relation": "oneToOne",
      "target": "api::industry.industry"
    }
  }
}
